rbwriter/__init__.py
rbwriter/checks.py
rbwriter/meta.py
rbwriter/views.py
rbwriter/wsgi.py
rbwriter/defines/__init__.py
rbwriter/defines/colormode.py
rbwriter/defines/colors.py
rbwriter/defines/configs.py
rbwriter/defines/messages.py
rbwriter/defines/paths.py
rbwriter/handlers/__init__.py
rbwriter/handlers/datehandler.py
rbwriter/handlers/dbhandler.py
rbwriter/handlers/pdfhandler.py
rbwriter/handlers/todolisthandler.py
rbwriter/models/__init__.py
rbwriter/models/message.py
rbwriter/models/messagequeue.py
rbwriter/models/user.py
rbwriter/static/styles/content_overview.css
rbwriter/static/styles/edit.css
rbwriter/static/styles/general.css
rbwriter/static/styles/index.css
rbwriter/static/styles/settings.css
rbwriter/static/styles/todolist.css
rbwriter/static/styles/user.css
rbwriter/static/styles/color/dark.css
rbwriter/static/styles/color/light.css
rbwriter/static/styles/security/change_password.css
rbwriter/static/styles/security/forgot_password.css
rbwriter/static/styles/security/login.css
rbwriter/static/styles/security/register.css
rbwriter/templates/base.html
rbwriter/templates/content_overview.html
rbwriter/templates/customedit.html
rbwriter/templates/edit.html
rbwriter/templates/index.html
rbwriter/templates/quickedit.html
rbwriter/templates/settings.html
rbwriter/templates/todolist.html
rbwriter/templates/user.html
rbwriter/templates/config/nginx.conf
rbwriter/templates/config/rbwriter_uwsgi.ini
rbwriter/templates/default/report_booklet_template_de.pdf
rbwriter/templates/default/todolist_template.json
rbwriter/templates/security/change_password.html
rbwriter/templates/security/forgot_password.html
rbwriter/templates/security/login.html
rbwriter/templates/security/register.html
rbwriter-0.1a2.data/scripts/rbwriter
rbwriter-0.1a2.dist-info/LICENSE
rbwriter-0.1a2.dist-info/METADATA
rbwriter-0.1a2.dist-info/WHEEL
rbwriter-0.1a2.dist-info/top_level.txt
rbwriter-0.1a2.dist-info/RECORD
