Metadata-Version: 2.1
Name: rbwriter
Version: 0.1a2
Summary: The Python web frontend to generate your pixel perfect report booklet
Home-page: https://github.com/TheCoder777/Report-Booklet-Writer
Author: Paul S.
Author-email: thecoder777.github@gmail.com
License: MIT
Project-URL: Source, https://github.com/TheCoder777/Report-Booklet-Writer
Project-URL: Issues, https://github.com/TheCoder777/Report-Booklet-Writer/issues
Keywords: front-end,frontend,frontend-web,web-application,frontend-app,report-booklet,booklet,writer
Platform: unix
Platform: linux
Platform: osx
Classifier: Development Status :: 2 - Pre-Alpha
Classifier: Environment :: Web Environment
Classifier: Framework :: Flask
Classifier: License :: OSI Approved :: MIT License
Classifier: Natural Language :: English
Classifier: Operating System :: MacOS :: MacOS X
Classifier: Operating System :: Unix
Classifier: Programming Language :: Python
Classifier: Programming Language :: Python :: 3
Classifier: Programming Language :: Python :: 3.6
Classifier: Programming Language :: Python :: 3.7
Classifier: Programming Language :: Python :: 3.8
Classifier: Programming Language :: Python :: 3.9
Classifier: Programming Language :: Python :: Implementation
Classifier: Topic :: Database
Classifier: Topic :: Database :: Front-Ends
Classifier: Topic :: Internet :: WWW/HTTP :: WSGI :: Application
Classifier: Topic :: Utilities
Requires-Python: >=3.6.0
